markapp/__init__.py
markapp/cli.py
markapp/markapp.py
markapp/watcher.py
markapp-0.3.1.dist-info/LICENSE
markapp-0.3.1.dist-info/METADATA
markapp-0.3.1.dist-info/WHEEL
markapp-0.3.1.dist-info/entry_points.txt
markapp-0.3.1.dist-info/top_level.txt
markapp-0.3.1.dist-info/RECORD
