Metadata-Version: 2.1
Name: markapp
Version: 0.3.1
Summary: A simple markdown to HTML compiler
Home-page: https://github.com/ddrscott/markapp
Author: Scott Pierce
Author-email: ddrscott@gmail.com
Classifier: Programming Language :: Python :: 3
Classifier: License :: OSI Approved :: MIT License
Classifier: Operating System :: OS Independent
Requires-Python: >=3.10
License-File: LICENSE
Requires-Dist: click
Requires-Dist: watchdog
